distributed_trajectories/OD.py
distributed_trajectories/TM.py
distributed_trajectories/__init__.py
distributed_trajectories/cli.py
distributed_trajectories/consts.py
distributed_trajectories/distributed_trajectories.py
distributed_trajectories/udfs.py
distributed_trajectories-0.1.0.dist-info/AUTHORS.rst
distributed_trajectories-0.1.0.dist-info/LICENSE
distributed_trajectories-0.1.0.dist-info/METADATA
distributed_trajectories-0.1.0.dist-info/WHEEL
distributed_trajectories-0.1.0.dist-info/entry_points.txt
distributed_trajectories-0.1.0.dist-info/top_level.txt
distributed_trajectories-0.1.0.dist-info/RECORD
