Metadata-Version: 2.1
Name: distributed-trajectories
Version: 0.1.0
Summary: Provides some basics for manipulation with the descrete distributed trajectories  with the Spark engine
Home-page: https://github.com/raalesir/distributed_trajectories
Author: Alexey Siretskiy
Author-email: alexey.siretskiy@gmail.com
License: GNU General Public License v3
Keywords: distributed_trajectories
Platform: UNKNOWN
Classifier: Development Status :: 2 - Pre-Alpha
Classifier: Intended Audience :: Developers
Classifier: License :: OSI Approved :: GNU General Public License v3 (GPLv3)
Classifier: Natural Language :: English
Classifier: Programming Language :: Python :: 3
Classifier: Programming Language :: Python :: 3.5
Classifier: Programming Language :: Python :: 3.6
Classifier: Programming Language :: Python :: 3.7
Classifier: Programming Language :: Python :: 3.8
Requires-Python: >=3.5
